{"metadata": {"dbt_schema_version": "https://schemas.getdbt.com/dbt/run-results/v6.json", "dbt_version": "1.11.11", "generated_at": "2026-07-02T17:19:16.148912Z", "invocation_id": "eaf19c31-1297-4804-97c4-158373d4f75d", "invocation_started_at": "2026-07-02T17:19:14.414487Z", "env": {}}, "results": [{"status": "success", "timing": [{"name": "compile", "started_at": "2026-07-02T17:19:16.081572Z", "completed_at": "2026-07-02T17:19:16.088097Z"}, {"name": "execute", "started_at": "2026-07-02T17:19:16.088436Z", "completed_at": "2026-07-02T17:19:16.088451Z"}], "thread_id": "Thread-1 (worker)", "execution_time": 0.007704496383666992, "adapter_response": {}, "message": null, "failures": null, "unique_id": "model.hw1.stg__smartphones", "compiled": true, "compiled_code": "\n\nSELECT \n    brand_name,\n    model,\n    price,\n    processor_brand,\n    num_cores::int,\n    processor_speed,\n    battery_capacity::int\nFROM \"dbt_course\".\"public\".\"smartphone_cleaned_v5\"\nWHERE num_cores > 0 --\u0414\u043e\u0431\u0430\u0432\u0438\u043b \u0434\u043b\u044f \u043f\u0440\u043e\u0432\u0435\u0440\u043a\u0438 \u044e\u043d\u0438\u0442 \u0442\u0435\u0441\u0442\u0430", "relation_name": "\"dbt_course\".\"smartphones\".\"stg_smartphones\"", "batch_results": null}, {"status": "success", "timing": [{"name": "compile", "started_at": "2026-07-02T17:19:16.090266Z", "completed_at": "2026-07-02T17:19:16.091534Z"}, {"name": "execute", "started_at": "2026-07-02T17:19:16.091848Z", "completed_at": "2026-07-02T17:19:16.091856Z"}], "thread_id": "Thread-1 (worker)", "execution_time": 0.0024824142456054688, "adapter_response": {}, "message": null, "failures": null, "unique_id": "seed.hw1.smartphone_cleaned_v5", "compiled": null, "compiled_code": null, "relation_name": null, "batch_results": null}, {"status": "success", "timing": [{"name": "compile", "started_at": "2026-07-02T17:19:16.093272Z", "completed_at": "2026-07-02T17:19:16.100938Z"}, {"name": "execute", "started_at": "2026-07-02T17:19:16.101282Z", "completed_at": "2026-07-02T17:19:16.101293Z"}], "thread_id": "Thread-1 (worker)", "execution_time": 0.00872945785522461, "adapter_response": {}, "message": null, "failures": null, "unique_id": "test.hw1.source_not_null_seed__smartfones_smartphones_brand_name.1e3986303f", "compiled": true, "compiled_code": "\n    \n    \n\n\n\nselect brand_name\nfrom \"dbt_course\".\"public\".\"smartphone_cleaned_v5\"\nwhere brand_name is null\n\n\n", "relation_name": null, "batch_results": null}, {"status": "success", "timing": [{"name": "compile", "started_at": "2026-07-02T17:19:16.102870Z", "completed_at": "2026-07-02T17:19:16.105863Z"}, {"name": "execute", "started_at": "2026-07-02T17:19:16.106129Z", "completed_at": "2026-07-02T17:19:16.106137Z"}], "thread_id": "Thread-1 (worker)", "execution_time": 0.004046440124511719, "adapter_response": {}, "message": null, "failures": null, "unique_id": "test.hw1.source_not_null_seed__smartfones_smartphones_model.e3cfcc1c07", "compiled": true, "compiled_code": "\n    \n    \n\n\n\nselect model\nfrom \"dbt_course\".\"public\".\"smartphone_cleaned_v5\"\nwhere model is null\n\n\n", "relation_name": null, "batch_results": null}, {"status": "success", "timing": [{"name": "compile", "started_at": "2026-07-02T17:19:16.107419Z", "completed_at": "2026-07-02T17:19:16.110160Z"}, {"name": "execute", "started_at": "2026-07-02T17:19:16.110507Z", "completed_at": "2026-07-02T17:19:16.110515Z"}], "thread_id": "Thread-1 (worker)", "execution_time": 0.003679990768432617, "adapter_response": {}, "message": null, "failures": null, "unique_id": "model.hw1.int__smartphones_brands", "compiled": true, "compiled_code": "\n\nSELECT DISTINCT\n  brand_name\nFROM \"dbt_course\".\"smartphones\".\"stg_smartphones\"", "relation_name": "\"dbt_course\".\"smartphones\".\"int_smartphones_brands\"", "batch_results": null}, {"status": "success", "timing": [{"name": "compile", "started_at": "2026-07-02T17:19:16.112640Z", "completed_at": "2026-07-02T17:19:16.116882Z"}, {"name": "execute", "started_at": "2026-07-02T17:19:16.117168Z", "completed_at": "2026-07-02T17:19:16.117176Z"}], "thread_id": "Thread-1 (worker)", "execution_time": 0.005890607833862305, "adapter_response": {}, "message": null, "failures": null, "unique_id": "model.hw1.int__smartphones_combination", "compiled": true, "compiled_code": "\n\nSELECT\n   \n    COALESCE(\n        processor_brand, \n        'Unknown'\n        )\n as processor_brand,\n   \n    COALESCE(\n        num_cores, \n        '-1'\n        )\n as num_cores,\n   \n    COALESCE(\n        processor_speed, \n        '-1'\n        )\n as processor_speed,\n   \n    COALESCE(\n        battery_capacity, \n        '-1'\n        )\n as battery_capacity,\n   COUNT(*) as combination_count \nFROM \"dbt_course\".\"smartphones\".\"stg_smartphones\"\nGROUP BY processor_brand,\n         num_cores,\n         processor_speed,\n         battery_capacity", "relation_name": "\"dbt_course\".\"smartphones\".\"int_smartphones_combination\"", "batch_results": null}, {"status": "success", "timing": [{"name": "compile", "started_at": "2026-07-02T17:19:16.118926Z", "completed_at": "2026-07-02T17:19:16.122579Z"}, {"name": "execute", "started_at": "2026-07-02T17:19:16.122899Z", "completed_at": "2026-07-02T17:19:16.122907Z"}], "thread_id": "Thread-1 (worker)", "execution_time": 0.004796266555786133, "adapter_response": {}, "message": null, "failures": null, "unique_id": "test.hw1.accepted_values_stg__smartphones_num_cores__2__4__6__8.ec4cfcc085", "compiled": true, "compiled_code": "\n    \n    \n\nwith all_values as (\n\n    select\n        num_cores as value_field,\n        count(*) as n_records\n\n    from \"dbt_course\".\"smartphones\".\"stg_smartphones\"\n    group by num_cores\n\n)\n\nselect *\nfrom all_values\nwhere value_field not in (\n    '2','4','6','8'\n)\n\n\n", "relation_name": null, "batch_results": null}, {"status": "success", "timing": [{"name": "compile", "started_at": "2026-07-02T17:19:16.124289Z", "completed_at": "2026-07-02T17:19:16.130682Z"}, {"name": "execute", "started_at": "2026-07-02T17:19:16.131053Z", "completed_at": "2026-07-02T17:19:16.131065Z"}], "thread_id": "Thread-1 (worker)", "execution_time": 0.007519721984863281, "adapter_response": {}, "message": null, "failures": null, "unique_id": "test.hw1.not_null_int__smartphones_brands_brand_name.728027bff3", "compiled": true, "compiled_code": "\n    \n    \n\n\n\nselect brand_name\nfrom \"dbt_course\".\"smartphones\".\"int_smartphones_brands\"\nwhere brand_name is null\n\n\n", "relation_name": null, "batch_results": null}, {"status": "success", "timing": [{"name": "compile", "started_at": "2026-07-02T17:19:16.132542Z", "completed_at": "2026-07-02T17:19:16.137159Z"}, {"name": "execute", "started_at": "2026-07-02T17:19:16.137415Z", "completed_at": "2026-07-02T17:19:16.137420Z"}], "thread_id": "Thread-1 (worker)", "execution_time": 0.005487918853759766, "adapter_response": {}, "message": null, "failures": null, "unique_id": "test.hw1.unique_int__smartphones_brands_brand_name.13d69236f0", "compiled": true, "compiled_code": "\n    \n    \n\nselect\n    brand_name as unique_field,\n    count(*) as n_records\n\nfrom \"dbt_course\".\"smartphones\".\"int_smartphones_brands\"\nwhere brand_name is not null\ngroup by brand_name\nhaving count(*) > 1\n\n\n", "relation_name": null, "batch_results": null}, {"status": "success", "timing": [{"name": "compile", "started_at": "2026-07-02T17:19:16.138746Z", "completed_at": "2026-07-02T17:19:16.141202Z"}, {"name": "execute", "started_at": "2026-07-02T17:19:16.141483Z", "completed_at": "2026-07-02T17:19:16.141488Z"}], "thread_id": "Thread-1 (worker)", "execution_time": 0.0033996105194091797, "adapter_response": {}, "message": null, "failures": null, "unique_id": "model.hw1.mart__proc_accum_top10", "compiled": true, "compiled_code": "\n\nSELECT\n    processor_brand,\n    num_cores,\n    processor_speed,\n    battery_capacity\nFROM \"dbt_course\".\"smartphones\".\"int_smartphones_combination\"\nORDER BY combination_count DESC\nLIMIT 10", "relation_name": "\"dbt_course\".\"smartphones\".\"mart_proc_accum_top10\"", "batch_results": null}, {"status": "success", "timing": [{"name": "compile", "started_at": "2026-07-02T17:19:16.143017Z", "completed_at": "2026-07-02T17:19:16.146580Z"}, {"name": "execute", "started_at": "2026-07-02T17:19:16.146912Z", "completed_at": "2026-07-02T17:19:16.146920Z"}], "thread_id": "Thread-1 (worker)", "execution_time": 0.004513263702392578, "adapter_response": {}, "message": null, "failures": null, "unique_id": "model.hw1.mart__proc_using_top10", "compiled": true, "compiled_code": "\nSELECT\n    processor_brand,\n    num_cores,\n    processor_speed\nFROM \"dbt_course\".\"smartphones\".\"int_smartphones_combination\"\nGROUP BY \n    processor_brand,\n    num_cores,\n    processor_speed\nORDER BY SUM(combination_count) DESC\nLIMIT 10", "relation_name": "\"dbt_course\".\"smartphones\".\"mart_proc_using_top10\"", "batch_results": null}], "elapsed_time": 0.24981331825256348, "args": {"require_all_warnings_handled_by_warn_error": false, "state_modified_compare_more_unrendered_values": false, "log_file_max_bytes": 10485760, "quiet": false, "which": "generate", "populate_cache": true, "sqlparse": {"MAX_GROUPING_DEPTH": null, "MAX_GROUPING_TOKENS": null}, "version_check": true, "log_format": "default", "require_unique_project_resource_names": false, "select": [], "log_path": "/home/arkrasouski/novadata/actions-runner/_work/7_dbt_advanced/7_dbt_advanced/dbt/hw1/logs", "profiles_dir": "/home/arkrasouski/.dbt", "require_generic_test_arguments_property": true, "write_json": true, "log_level": "info", "defer": false, "printer_width": 80, "log_level_file": "debug", "cache_selected_only": false, "require_explicit_package_overrides_for_builtin_materializations": true, "static_parser": true, "source_freshness_run_project_hooks": true, "show_resource_report": false, "partial_parse": true, "print": true, "skip_nodes_if_on_run_start_fails": false, "exclude": [], "introspect": true, "show_all_deprecations": false, "use_fast_test_edges": false, "use_colors_file": true, "log_format_file": "debug", "target": "dev", "upload_to_artifacts_ingest_api": false, "indirect_selection": "eager", "partial_parse_file_diff": true, "compile": true, "require_yaml_configuration_for_mf_time_spines": false, "state_modified_compare_vars": false, "macro_debugging": false, "warn_error_options": {"error": [], "warn": [], "silence": []}, "empty_catalog": false, "strict_mode": false, "static": false, "favor_state": false, "vars": {}, "invocation_command": "dbt docs generate --target dev", "project_dir": "/home/arkrasouski/novadata/actions-runner/_work/7_dbt_advanced/7_dbt_advanced/dbt/hw1", "require_resource_names_without_spaces": true, "require_ref_searches_node_package_before_root": false, "require_batched_execution_for_custom_microbatch_strategy": false, "require_nested_cumulative_type_params": false, "use_colors": true, "validate_macro_args": false, "send_anonymous_usage_stats": true}}